{
  "data": {
    "article": {},
    "attachments": {},
    "author_id": "1638959586140098560",
    "conversation_id": "2069276456400896480",
    "created_at": "2026-06-23T05:35:08.000Z",
    "edit_controls": {
      "editable_until": "2026-06-23T06:35:08.000Z",
      "edits_remaining": 5,
      "is_edit_eligible": false
    },
    "edit_history_tweet_ids": [
      "2069293154491306106"
    ],
    "entities": {
      "mentions": [
        {
          "end": 10,
          "id": "2063957681984225280",
          "start": 0,
          "username": "YuwenMewo"
        },
        {
          "end": 20,
          "id": "2057729979677548544",
          "start": 11,
          "username": "Numiouoo"
        }
      ]
    },
    "geo": {},
    "id": "2069293154491306106",
    "in_reply_to_user_id": "2063957681984225280",
    "lang": "zh",
    "note_tweet": {
      "entities": {}
    },
    "possibly_sensitive": false,
    "public_metrics": {
      "bookmark_count": 0,
      "impression_count": 0,
      "like_count": 0,
      "quote_count": 0,
      "reply_count": 0,
      "retweet_count": 0
    },
    "referenced_tweets": [
      {
        "id": "2069292695550648601",
        "type": "replied_to"
      }
    ],
    "reply_settings": "everyone",
    "text": "@YuwenMewo @Numiouoo 羡慕操操逼环节"
  },
  "includes": {
    "tweets": [
      {
        "article": {},
        "attachments": {},
        "author_id": "1638959586140098560",
        "conversation_id": "2069276456400896480",
        "created_at": "2026-06-23T05:35:08.000Z",
        "edit_controls": {
          "editable_until": "2026-06-23T06:35:08.000Z",
          "edits_remaining": 5,
          "is_edit_eligible": false
        },
        "edit_history_tweet_ids": [
          "2069293154491306106"
        ],
        "entities": {
          "mentions": [
            {
              "end": 10,
              "id": "2063957681984225280",
              "start": 0,
              "username": "YuwenMewo"
            },
            {
              "end": 20,
              "id": "2057729979677548544",
              "start": 11,
              "username": "Numiouoo"
            }
          ]
        },
        "geo": {},
        "id": "2069293154491306106",
        "in_reply_to_user_id": "2063957681984225280",
        "lang": "zh",
        "note_tweet": {
          "entities": {}
        },
        "possibly_sensitive": false,
        "public_metrics": {
          "bookmark_count": 0,
          "impression_count": 0,
          "like_count": 0,
          "quote_count": 0,
          "reply_count": 0,
          "retweet_count": 0
        },
        "referenced_tweets": [
          {
            "id": "2069292695550648601",
            "type": "replied_to"
          }
        ],
        "reply_settings": "everyone",
        "text": "@YuwenMewo @Numiouoo 羡慕操操逼环节"
      },
      {
        "article": {},
        "attachments": {},
        "author_id": "2063957681984225280",
        "conversation_id": "2069276456400896480",
        "created_at": "2026-06-23T05:33:18.000Z",
        "edit_controls": {
          "editable_until": "2026-06-23T06:33:18.000Z",
          "edits_remaining": 5,
          "is_edit_eligible": false
        },
        "edit_history_tweet_ids": [
          "2069292695550648601"
        ],
        "entities": {
          "mentions": [
            {
              "end": 9,
              "id": "2057729979677548544",
              "start": 0,
              "username": "Numiouoo"
            },
            {
              "end": 20,
              "id": "1638959586140098560",
              "start": 10,
              "username": "fanwei_17"
            }
          ]
        },
        "geo": {},
        "id": "2069292695550648601",
        "in_reply_to_user_id": "2057729979677548544",
        "lang": "zh",
        "note_tweet": {
          "entities": {}
        },
        "possibly_sensitive": false,
        "public_metrics": {
          "bookmark_count": 0,
          "impression_count": 7,
          "like_count": 0,
          "quote_count": 0,
          "reply_count": 1,
          "retweet_count": 0
        },
        "referenced_tweets": [
          {
            "id": "2069292161582215246",
            "type": "replied_to"
          }
        ],
        "reply_settings": "everyone",
        "text": "@Numiouoo @fanwei_17 你就说有没有吧 不发起码给我意淫一下操操逼环节🤓"
      }
    ],
    "users": [
      {
        "created_at": "2023-03-23T17:43:19.000Z",
        "description": "无性别enby/药理help/互fo评论/偏爱:@Numiouoo/友跨友同友全部",
        "entities": {
          "description": {
            "mentions": [
              {
                "end": 33,
                "start": 24,
                "username": "Numiouoo"
              }
            ]
          }
        },
        "id": "1638959586140098560",
        "location": "Thrillingly pointless",
        "name": "反胃的Sisyphus",
        "pinned_tweet_id": "2051091519847698605",
        "profile_image_url": "https://pbs.twimg.com/profile_images/2043493826246082560/syYxrkxW_normal.jpg",
        "protected": false,
        "public_metrics": {
          "followers_count": 2421,
          "following_count": 1553,
          "like_count": 5573,
          "listed_count": 3,
          "media_count": 49,
          "tweet_count": 2504
        },
        "url": "",
        "username": "fanwei_17",
        "verified": false
      },
      {
        "created_at": "2026-06-08T12:21:21.000Z",
        "description": "🏳️‍⚧️ MTF ♀\n🎂 10.19\n💉 HRT 2025.06.30\n🍥  持证含糖\n💻 科技宅一只\n✨ 努力长成理想中的自己",
        "id": "2063957681984225280",
        "name": "唐毓文",
        "pinned_tweet_id": "2068867775406448996",
        "profile_image_url": "https://pbs.twimg.com/profile_images/2063959820148064256/gZr_9bTC_normal.jpg",
        "protected": false,
        "public_metrics": {
          "followers_count": 628,
          "following_count": 38,
          "like_count": 121,
          "listed_count": 4,
          "media_count": 268,
          "tweet_count": 826
        },
        "url": "",
        "username": "YuwenMewo",
        "verified": true
      },
      {
        "created_at": "2026-05-22T07:47:58.000Z",
        "description": "糯米守护大家🩷爱与和平🩷偏爱:@fanwei_17\n疯狗神经病绝赞死毒虫🩵Sex&Drug&Harm激推🩵评论互动查成分回fo(互关重生直接d我!)🩵我素non-binary 友跨友全部 🩵请勿私信⚠️⚠️⚠️",
        "entities": {
          "description": {
            "mentions": [
              {
                "end": 25,
                "start": 15,
                "username": "fanwei_17"
              }
            ]
          }
        },
        "id": "2057729979677548544",
        "name": "糯米🍬纸 (4.0寻回互关",
        "pinned_tweet_id": "2057737015958057252",
        "profile_image_url": "https://pbs.twimg.com/profile_images/2062168596797923328/CUlw6WHk_normal.jpg",
        "protected": false,
        "public_metrics": {
          "followers_count": 1434,
          "following_count": 916,
          "like_count": 2631,
          "listed_count": 0,
          "media_count": 25,
          "tweet_count": 2075
        },
        "url": "",
        "username": "Numiouoo",
        "verified": false
      }
    ]
  }
}